acms.py
acms-0.1.0.dist-info/licenses/LICENSE
acms-0.1.0.dist-info/METADATA
acms-0.1.0.dist-info/WHEEL
acms-0.1.0.dist-info/entry_points.txt
acms-0.1.0.dist-info/top_level.txt
acms-0.1.0.dist-info/RECORD
