Metadata-Version: 2.4
Name: ACMS
Version: 0.1.0
Summary: ACMS is a Model Context Protocol (MCP) server that provides programmatic access to Apple's container CLI tool on macOS.
Author-email: Joe Gatt <gattjoe@users.noreply.github.com>
License-Expression: Apache-2.0
Project-URL: homepage, https://github.com/gattjoe/ACMS
Project-URL: documentation, https://github.com/gattjoe/ACMS/blob/master/README.md
Project-URL: repository, https://github.com/gattjoe/ACMS
Project-URL: changelog, https://github.com/gattjoe/ACMS/blob/master/CHANGELOG.md
Keywords: AI, Apple, MCP, container
Classifier: Programming Language :: Python :: 3
Classifier: Programming Language :: Python :: 3.9
Classifier: Programming Language :: Python :: 3.10
Classifier: Programming Language :: Python :: 3.11
Classifier: Programming Language :: Python :: 3.12
Classifier: Programming Language :: Python :: 3.13
Requires-Python: >=3.9
License-File: LICENSE
Requires-Dist: fastmcp>=2.14
Requires-Dist: mcp<2,>=1.25
Dynamic: license-file
